LibraryApp-3.1.0.data/scripts/docs_app
LibraryApp-3.1.0.data/scripts/locallibrary_app
catalog/__init__.py
catalog/admin.py
catalog/apps.py
catalog/forms.py
catalog/models.py
catalog/serializers.py
catalog/urls.py
catalog/views.py
catalog/__pycache__/__init__.cpython-36.pyc
catalog/__pycache__/admin.cpython-36.pyc
catalog/__pycache__/forms.cpython-36.pyc
catalog/__pycache__/models.cpython-36.pyc
catalog/__pycache__/serializers.cpython-36.pyc
catalog/__pycache__/urls.cpython-36.pyc
catalog/__pycache__/views.cpython-36.pyc
catalog/migrations/0001_initial.py
catalog/migrations/0002_auto_20190708_1432.py
catalog/migrations/0003_auto_20190722_1143.py
catalog/migrations/__init__.py
catalog/migrations/__pycache__/0001_initial.cpython-36.pyc
catalog/migrations/__pycache__/0002_auto_20190708_1432.cpython-36.pyc
catalog/migrations/__pycache__/0003_auto_20190722_1143.cpython-36.pyc
catalog/migrations/__pycache__/__init__.cpython-36.pyc
catalog/static/css/style.css
catalog/templates/base_generic.html
catalog/templates/index.html
catalog/templates/catalog/author_confirm_delete.html
catalog/templates/catalog/author_detail.html
catalog/templates/catalog/author_form.html
catalog/templates/catalog/author_list.html
catalog/templates/catalog/book_confirm_delete.html
catalog/templates/catalog/book_detail.html
catalog/templates/catalog/book_form.html
catalog/templates/catalog/book_list.html
catalog/templates/catalog/book_renew_librarian.html
catalog/templates/catalog/bookinstance_list_borrowed_all.html
catalog/templates/catalog/bookinstance_list_borrowed_user.html
catalog/templates/catalog/periodic_email_body.html
catalog/templates/catalog/periodic_email_subject.html
catalog/templates/catalog/{{ book.get_absolute_url }}
catalog/templates/registration/logged_out.html
catalog/templates/registration/login.html
catalog/templates/registration/password_reset-done.html
catalog/templates/registration/password_reset_complete.html
catalog/templates/registration/password_reset_confirm.html
LibraryApp-3.1.0.dist-info/LICENSE
LibraryApp-3.1.0.dist-info/METADATA
LibraryApp-3.1.0.dist-info/WHEEL
LibraryApp-3.1.0.dist-info/top_level.txt
LibraryApp-3.1.0.dist-info/RECORD
