Metadata-Version: 2.1
Name: LibraryApp
Version: 3.1.0
Summary: A simple django library app 
Home-page: UNKNOWN
Author: kevin
Author-email: kevin@kev.com
License: MIT License
Platform: UNKNOWN
Classifier: Environment :: Web Environment
Classifier: Framework :: Django :: 2.1
Classifier: Framework :: Django :: 2.2
Classifier: Intended Audience :: Developers
Classifier: License :: OSI Approved :: MIT License
Requires-Dist: Django (<=2.2.2,>=1.11.22)
Requires-Dist: celery (>=3.1.16)
Requires-Dist: django-environ (==0.4.5)
Requires-Dist: djangorestframework (==3.9.4)
Requires-Dist: psycopg2 (==2.8.3)
Requires-Dist: social-auth-app-django (==3.1.0)
Requires-Dist: whitenoise (==4.1.3)
